ucal/__init__.py
ucal/ucal.py
ucal/ucal_units.py
ucal_gui/BaseCalculatorWindow.py
ucal_gui/__init__.py
ucal_gui/__main__.py
ucal_gui/ucal.ico
ucal_gui/ucal_gui.py
ucal-1.3.5.dist-info/LICENSE
ucal-1.3.5.dist-info/METADATA
ucal-1.3.5.dist-info/WHEEL
ucal-1.3.5.dist-info/top_level.txt
ucal-1.3.5.dist-info/RECORD
