Metadata-Version: 2.1
Name: ucal
Version: 1.3.5
Summary: A calculator with automatic unit conversions
Home-page: https://github.com/timkostka/ucal
Author: Tim Kostka
Author-email: kostka@gmail.com
License: UNKNOWN
Platform: UNKNOWN
Classifier: Programming Language :: Python :: 3
Classifier: License :: OSI Approved :: GNU General Public License v3 (GPLv3)
Classifier: Operating System :: OS Independent
Requires-Dist: pyperclip
Requires-Dist: wxPython
